{
  "exp": "cpsam_modal",
  "arch": "cellpose",
  "per_fov": [
    {
      "fov": "FOV_036",
      "ari": 0.8235177456012308,
      "gt_cells": 66,
      "pred_cells": 75,
      "missed_cells": 6,
      "spurious_cells": 13,
      "split_cells": 0,
      "merged_cells": 1,
      "n_spots": 50077,
      "correct_cell": 12190,
      "wrong_cell": 47,
      "false_positive": 2151,
      "false_negative": 947,
      "correct_bg": 34742
    },
    {
      "fov": "FOV_037",
      "ari": 0.8523958111426482,
      "gt_cells": 94,
      "pred_cells": 107,
      "missed_cells": 1,
      "spurious_cells": 14,
      "split_cells": 0,
      "merged_cells": 0,
      "n_spots": 56089,
      "correct_cell": 17966,
      "wrong_cell": 77,
      "false_positive": 2591,
      "false_negative": 561,
      "correct_bg": 34894
    },
    {
      "fov": "FOV_038",
      "ari": 0.7503785378238564,
      "gt_cells": 111,
      "pred_cells": 130,
      "missed_cells": 9,
      "spurious_cells": 24,
      "split_cells": 1,
      "merged_cells": 0,
      "n_spots": 70272,
      "correct_cell": 22567,
      "wrong_cell": 89,
      "false_positive": 5426,
      "false_negative": 1474,
      "correct_bg": 40716
    },
    {
      "fov": "FOV_039",
      "ari": 0.7744173179042534,
      "gt_cells": 82,
      "pred_cells": 94,
      "missed_cells": 9,
      "spurious_cells": 19,
      "split_cells": 2,
      "merged_cells": 0,
      "n_spots": 62342,
      "correct_cell": 17534,
      "wrong_cell": 63,
      "false_positive": 3743,
      "false_negative": 1579,
      "correct_bg": 39423
    },
    {
      "fov": "FOV_040",
      "ari": 0.8741034263674045,
      "gt_cells": 67,
      "pred_cells": 72,
      "missed_cells": 4,
      "spurious_cells": 8,
      "split_cells": 0,
      "merged_cells": 0,
      "n_spots": 60352,
      "correct_cell": 16349,
      "wrong_cell": 73,
      "false_positive": 2113,
      "false_negative": 612,
      "correct_bg": 41205
    }
  ],
  "mean_ari": 0.8149625677678787,
  "total_missed": 29,
  "total_spurious": 78,
  "total_split": 3,
  "total_merged": 1,
  "total_wrong_cell": 349,
  "total_false_positive": 16024,
  "total_false_negative": 5173
}